ksp_login/TODO
ksp_login/__init__.py
ksp_login/backends.py
ksp_login/context_processors.py
ksp_login/forms.py
ksp_login/locale/sk/LC_MESSAGES/django.mo
ksp_login/locale/sk/LC_MESSAGES/django.po
ksp_login/models.py
ksp_login/pipeline.py
ksp_login/static/ksp_login/css/base.css
ksp_login/static/ksp_login/img/close.svg
ksp_login/static/ksp_login/img/facebook.png
ksp_login/static/ksp_login/img/github.png
ksp_login/static/ksp_login/img/google-oauth2.png
ksp_login/static/ksp_login/img/google.png
ksp_login/static/ksp_login/img/launchpad.png
ksp_login/static/ksp_login/img/loga100.zip
ksp_login/static/ksp_login/img/myopenid.png
ksp_login/static/ksp_login/img/openid.png
ksp_login/static/ksp_login/img/sources.txt
ksp_login/static/ksp_login/img/twitter.png
ksp_login/static/ksp_login/js/backend_list.js
ksp_login/static/ksp_login/js/jquery.init.js
ksp_login/static/ksp_login/js/jquery.simplemodal.1.4.4.min.js
ksp_login/static/ksp_login/js/jquery.simplemodal.js
ksp_login/templates/ksp_login/base.html
ksp_login/templates/ksp_login/invalid_disconnect.html
ksp_login/templates/ksp_login/login.html
ksp_login/templates/ksp_login/parts/associated_accounts_list.html
ksp_login/templates/ksp_login/parts/backend_list.html
ksp_login/templates/ksp_login/parts/include_javascript.html
ksp_login/templates/ksp_login/parts/login_box.html
ksp_login/templates/ksp_login/parts/login_full_contents.html
ksp_login/templates/ksp_login/parts/multiple_forms.html
ksp_login/templates/ksp_login/parts/single_form.html
ksp_login/templates/ksp_login/password.html
ksp_login/templates/ksp_login/password_reset_complete.html
ksp_login/templates/ksp_login/password_reset_confirm.html
ksp_login/templates/ksp_login/password_reset_done.html
ksp_login/templates/ksp_login/password_reset_email.txt
ksp_login/templates/ksp_login/password_reset_form.html
ksp_login/templates/ksp_login/password_reset_subject.txt
ksp_login/templates/ksp_login/registration.html
ksp_login/templates/ksp_login/settings.html
ksp_login-0.6.2.dist-info/LICENSE
ksp_login-0.6.2.dist-info/WHEEL
ksp_login-0.6.2.dist-info/METADATA
ksp_login-0.6.2.dist-info/RECORD
